llama_index/_bundle/__init__.py
llama_index-0.14.1.dist-info/METADATA
llama_index-0.14.1.dist-info/WHEEL
llama_index-0.14.1.dist-info/entry_points.txt
llama_index-0.14.1.dist-info/licenses/LICENSE
llama_index-0.14.1.dist-info/RECORD
