Metadata-Version: 2.4
Name: llama-index
Version: 0.14.1
Summary: Interface between LLMs and your data
Project-URL: Documentation, https://docs.llamaindex.ai/en/stable/
Project-URL: Homepage, https://llamaindex.ai
Project-URL: Repository, https://github.com/run-llama/llama_index
Author-email: Jerry Liu <jerry@llamaindex.ai>
Maintainer-email: Andrei Fajardo <andrei@runllama.ai>, Haotian Zhang <ht@runllama.ai>, Jerry Liu <jerry@llamaindex.ai>, Logan Markewich <logan@llamaindex.ai>, Simon Suo <simon@llamaindex.ai>, Sourabh Desai <sourabh@llamaindex.ai>
License-Expression: MIT
License-File: LICENSE
Keywords: LLM,NLP,RAG,data,devtools,index,retrieval
Classifier: Topic :: Scientific/Engineering :: Artificial Intelligence
Classifier: Topic :: Software Development :: Libraries :: Application Frameworks
Classifier: Topic :: Software Development :: Libraries :: Python Modules
Requires-Python: <4.0,>=3.9
Requires-Dist: llama-index-cli<0.6,>=0.5.0
Requires-Dist: llama-index-core<0.15,>=0.14.1
Requires-Dist: llama-index-embeddings-openai<0.6,>=0.5.0
Requires-Dist: llama-index-indices-managed-llama-cloud>=0.4.0
Requires-Dist: llama-index-llms-openai<0.6,>=0.5.0
Requires-Dist: llama-index-readers-file<0.6,>=0.5.0
Requires-Dist: llama-index-readers-llama-parse>=0.4.0
Requires-Dist: nltk>3.8.1
